login_canaime/__init__.py
login_canaime/autenticador.py
login_canaime/auth.py
login_canaime/cli.py
login_canaime/py.typed
login_canaime/ui/__init__.py
login_canaime/ui/tkinter_ui.py
login_canaime-2.0.0.dist-info/LICENSE
login_canaime-2.0.0.dist-info/METADATA
login_canaime-2.0.0.dist-info/WHEEL
login_canaime-2.0.0.dist-info/entry_points.txt
login_canaime-2.0.0.dist-info/top_level.txt
login_canaime-2.0.0.dist-info/RECORD
