Metadata-Version: 2.2
Name: login-canaime
Version: 2.0.0
Summary: Biblioteca para autenticação no sistema Canaimé e manipulação da página logada
Author-email: Anderson Assunção <andersongomesrr@hotmail.com>
License: # MIT License
Project-URL: Homepage, https://github.com/A-Assuncao/login-canaime
Project-URL: Bug Tracker, https://github.com/A-Assuncao/login-canaime/issues
Project-URL: Documentation, https://github.com/A-Assuncao/login-canaime/blob/main/README.md
Classifier: Development Status :: 5 - Production/Stable
Classifier: Intended Audience :: Developers
Classifier: License :: OSI Approved :: MIT License
Classifier: Programming Language :: Python :: 3
Classifier: Programming Language :: Python :: 3.8
Classifier: Programming Language :: Python :: 3.9
Classifier: Programming Language :: Python :: 3.10
Classifier: Programming Language :: Python :: 3.11
Classifier: Topic :: Software Development :: Libraries
Requires-Python: >=3.8
License-File: LICENSE
Requires-Dist: playwright>=1.28.0
